Metadata-Version: 2.1
Name: objax
Version: 1.8.0
Summary: Objax is a machine learning framework that provides an Object Oriented layer for JAX.
Home-page: https://github.com/google/objax
Author: Objax team
Author-email: objax-dev@google.com
Classifier: Development Status :: 5 - Production/Stable
Classifier: Intended Audience :: Developers
Classifier: Intended Audience :: Science/Research
Classifier: License :: OSI Approved :: Apache Software License
Classifier: Programming Language :: Python :: 3.9
Classifier: Programming Language :: Python :: 3.10
Classifier: Programming Language :: Python :: 3.11
Classifier: Topic :: Scientific/Engineering :: Artificial Intelligence
License-File: LICENSE
Requires-Dist: scipy
Requires-Dist: numpy >=1.18.0
Requires-Dist: pillow
Requires-Dist: jaxlib >=0.4.19
Requires-Dist: jax >=0.3.25
Requires-Dist: tensorboard >=2.3.0
Requires-Dist: parameterized
